README.md
setup.py
automation_common_test.egg-info/PKG-INFO
automation_common_test.egg-info/SOURCES.txt
automation_common_test.egg-info/dependency_links.txt
automation_common_test.egg-info/top_level.txt
helpers/__init__.py
helpers/api_operations.py
helpers/base_locator.py
helpers/decorator.py
helpers/driver_manager.py
helpers/soft_check.py
helpers/web_operations.py
utils/__init__.py
utils/config_parser.py
utils/encryption_decryption.py
utils/excel_utils.py
utils/json_utils.py
utils/post_results_teams.py