Metadata-Version: 2.1
Name: automation-common-test
Version: 2.10.4
Summary: This is the common automation framework
Author: Chitranjan Kumar
Author-email: chitranjan.kumar@kyndryl.com
License: Kyndryl
